{
  "parent": "minecraft:recipes/root",
  "criteria": {
    "has_polished_deepslate": {
      "conditions": {
        "items": [
          {
            "items": [
              "minecraft:polished_deepslate"
            ]
          }
        ]
      },
      "trigger": "minecraft:inventory_changed"
    },
    "has_the_recipe": {
      "conditions": {
        "recipe": "blockus:polished_deepslate_pressure_plate"
      },
      "trigger": "minecraft:recipe_unlocked"
    }
  },
  "requirements": [
    [
      "has_polished_deepslate",
      "has_the_recipe"
    ]
  ],
  "rewards": {
    "recipes": [
      "blockus:polished_deepslate_pressure_plate"
    ]
  }
}