{
  "parent": "minecraft:recipes/root",
  "criteria": {
    "has_beveled_glass_pane": {
      "conditions": {
        "items": [
          {
            "items": [
              "blockus:purple_beveled_glass"
            ]
          }
        ]
      },
      "trigger": "minecraft:inventory_changed"
    },
    "has_the_recipe": {
      "conditions": {
        "recipe": "blockus:purple_beveled_glass_pane"
      },
      "trigger": "minecraft:recipe_unlocked"
    }
  },
  "requirements": [
    [
      "has_beveled_glass_pane",
      "has_the_recipe"
    ]
  ],
  "rewards": {
    "recipes": [
      "blockus:purple_beveled_glass_pane"
    ]
  },
  "sends_telemetry_event": false
}